{
    "About": {
        "Address": "441, Galle Road, Colombo 03, Sri Lanka., Colombo, Sri Lanka, 00300",
        "Contact": "0117 463 463"
    },
    "Recommendation": "not available",
    "Reviews": [
        {
            "User": "Makeen Books",
            "Review": "No review text"
        },
        {
            "User": "Makeen Books",
            "Review": "No review text"
        },
        {
            "User": "Makeen Books",
            "Review": "No review text"
        },
        {
            "User": "Makeen Books",
            "Review": "No review text"
        },
        {
            "User": "Makeen Books",
            "Review": "No review text"
        },
        {
            "User": "Makeen Books",
            "Review": "No review text"
        }
    ],
    "Posts": [
        {
            "Post Content": "Books, books, and more books!  Our little reader had the best time at the Makeen Books Mega Sale! Nothing beats the joy of finding a new favorite story. … See more",
            "Comments": [],
            "Reactions": {},
            "Timestamp": "2025-04-28T23:13:57.503182"
        },
        {
            "Post Content": "Books, books, and more books!  Our little reader had the best time at the Makeen Books Mega Sale! Nothing beats the joy of finding a new favorite story. … See more",
            "Comments": [],
            "Reactions": {},
            "Timestamp": "2025-04-28T23:13:57.533384"
        },
        {
            "Post Content": "Books, books, and more books!  Our little reader had the best time at the Makeen Books Mega Sale! Nothing beats the joy of finding a new favorite story. … See more",
            "Comments": [],
            "Reactions": {},
            "Timestamp": "2025-04-28T23:13:57.566215"
        },
        {
            "Post Content": "Books, books, and more books!  Our little reader had the best time at the Makeen Books Mega Sale! Nothing beats the joy of finding a new favorite story. … See more",
            "Comments": [],
            "Reactions": {},
            "Timestamp": "2025-04-28T23:13:57.577671"
        },
        {
            "Post Content": "Books, books, and more books!  Our little reader had the best time at the Makeen Books Mega Sale! Nothing beats the joy of finding a new favorite story. … See more",
            "Comments": [],
            "Reactions": {
                "Love": 3,
                "Like": 2
            },
            "Timestamp": "2025-04-28T23:13:57.600447"
        },
        {
            "Post Content": "What Our Customers Are Saying! Wi… See more",
            "Comments": [],
            "Reactions": {
                "Like": 1,
                "Care": 1
            },
            "Timestamp": "2025-04-28T23:13:57.622369"
        },
        {
            "Post Content": "Loved by Readers, Priced for You! O… See more",
            "Comments": [],
            "Reactions": {
                "Like": 2
            },
            "Timestamp": "2025-04-28T23:13:57.643983"
        },
        {
            "Post Content": "Real Readers, Real Reviews! O… See more",
            "Comments": [],
            "Reactions": {
                "Like": 2,
                "Love": 1
            },
            "Timestamp": "2025-04-28T23:13:57.666915"
        },
        {
            "Post Content": "Another Happy Reader at the Makeen Mega Book Sale! N… See more",
            "Comments": [],
            "Reactions": {
                "Like": 1,
                "Love": 1
            },
            "Timestamp": "2025-04-28T23:13:57.687039"
        },
        {
            "Post Content": "Makeen Mega Book Sale – What Our Customers Say! B… See more",
            "Comments": [],
            "Reactions": {
                "Love": 1
            },
            "Timestamp": "2025-04-28T23:13:57.706884"
        },
        {
            "Post Content": "Great News, Book Lovers! G… See more",
            "Comments": [],
            "Reactions": {},
            "Timestamp": "2025-04-28T23:13:57.727024"
        },
        {
            "Post Content": "Real Reviews, Real Experiences! Watch what our happy customers have to say!See what our happy readers say about their book haul from the Mega Book Sale!  From b… See more",
            "Comments": [],
            "Reactions": {
                "Like": 3,
                "Love": 2
            },
            "Timestamp": "2025-04-28T23:13:57.743748"
        },
        {
            "Post Content": "RESTOCKING FOR DAY 2 – MEGA SALE CONTINUES! D… See more",
            "Comments": [],
            "Reactions": {
                "Like": 4,
                "Love": 2
            },
            "Timestamp": "2025-04-28T23:13:57.766233"
        },
        {
            "Post Content": "Another Happy Reader – Mega Book Sale at Makeen Books! O… See more",
            "Comments": [],
            "Reactions": {
                "Like": 5,
                "Love": 2
            },
            "Timestamp": "2025-04-28T23:13:57.782092"
        },
        {
            "Post Content": "Readers Love the Mega Book Sale at Makeen Books! A… See more",
            "Comments": [],
            "Reactions": {
                "Love": 2,
                "Like": 1
            },
            "Timestamp": "2025-04-28T23:13:57.801308"
        },
        {
            "Post Content": "Customer Reviews Are In – Makeen Books Mega Sale is Unmissable!… See more",
            "Comments": [],
            "Reactions": {
                "Like": 5,
                "Love": 1
            },
            "Timestamp": "2025-04-28T23:13:57.821155"
        },
        {
            "Post Content": "Hear It from Our Happy Readers!Our customers are loving the MEGA BOOK SALE at Makeen Books!  With discounts up to 50%, it’s the perfect time to grab your favorite rea… See more",
            "Comments": [],
            "Reactions": {
                "Like": 5,
                "Love": 3
            },
            "Timestamp": "2025-04-28T23:13:57.842690"
        },
        {
            "Post Content": "\" Snag the BEST deals before they’re gone!  Shop now and save big—your wallet will thank you! Our … See more",
            "Comments": [],
            "Reactions": {
                "Like": 2,
                "Love": 1
            },
            "Timestamp": "2025-04-28T23:13:57.860017"
        },
        {
            "Post Content": "MEGA BOOK SALE ALERT! G… See more",
            "Comments": [],
            "Reactions": {
                "Like": 10,
                "Love": 5
            },
            "Timestamp": "2025-04-28T23:13:57.878129"
        },
        {
            "Post Content": "Current Bestsellers You Can’t Miss! … See more",
            "Comments": [],
            "Reactions": {},
            "Timestamp": "2025-04-28T23:13:57.938606"
        },
        {
            "Post Content": "Current Bestsellers You Can’t Miss! … See more",
            "Comments": [],
            "Reactions": {},
            "Timestamp": "2025-04-28T23:13:57.990494"
        },
        {
            "Post Content": "Current Bestsellers You Can’t Miss! … See more",
            "Comments": [],
            "Reactions": {},
            "Timestamp": "2025-04-28T23:13:58.027976"
        },
        {
            "Post Content": "Current Bestsellers You Can’t Miss! … See more",
            "Comments": [],
            "Reactions": {
                "Like": 1
            },
            "Timestamp": "2025-04-28T23:13:58.054492"
        },
        {
            "Post Content": "Find Your School’s Required Literature Books at Makeen Books! … See more",
            "Comments": [],
            "Reactions": {},
            "Timestamp": "2025-04-28T23:13:58.089001"
        },
        {
            "Post Content": "Find Your School’s Required Literature Books at Makeen Books! … See more",
            "Comments": [],
            "Reactions": {
                "Love": 1
            },
            "Timestamp": "2025-04-28T23:13:58.110989"
        },
        {
            "Post Content": "After a week-long break, Makeen Books is open and ready to welcome you again! We've missed you and can't wait to help you discover your next favorite read.… See more",
            "Comments": [],
            "Reactions": {
                "Like": 2
            },
            "Timestamp": "2025-04-28T23:13:58.129577"
        },
        {
            "Post Content": "Important Announcement!Our showroom will be closed on Saturday(18th January 2025) for stock-taking and will reopen on Monday, 20th January.… See more",
            "Comments": [],
            "Reactions": {
                "Like": 3,
                "Love": 1
            },
            "Timestamp": "2025-04-28T23:13:58.156486"
        },
        {
            "Post Content": "Dive into the dark and gripping worlds of Alex Michaelides! Explore The Silent Patient, a psychological masterpiece with a twist that will leave you stunned, and The… See more",
            "Comments": [],
            "Reactions": {
                "Like": 3,
                "Love": 2
            },
            "Timestamp": "2025-04-28T23:13:58.172899"
        },
        {
            "Post Content": "No Text",
            "Comments": [],
            "Reactions": {},
            "Timestamp": "2025-04-28T23:13:58.181751"
        },
        {
            "Post Content": "No Text",
            "Comments": [],
            "Reactions": {},
            "Timestamp": "2025-04-28T23:13:58.189749"
        }
    ]
}